{"type":"ugc","codecid":7,"groupId":"BV1yt411S7ks","itemId":66158339,"aid":37630789,"cid":66158339,"bvid":"BV1yt411S7ks","p":1,"tabP":0,"tabName":"【动漫风景混剪】二次元里的风花雪月。","uid":"23021457","uname":"__TAKU","avatar":"https://i0.hdslb.com/bfs/face/4e7891fae802a3b417a40e5e2c61b30fc742c3b1.jpg","coverUrl":"http://i0.hdslb.com/bfs/archive/6c0af53821870cbb5b075ab5b164b785addc39e0.jpg","title":"【动漫风景混剪】二次元里的风花雪月。","duration":225,"groupTitle":"【动漫风景混剪】二次元里的风花雪月。","groupCoverUrl":"http://i0.hdslb.com/bfs/archive/6c0af53821870cbb5b075ab5b164b785addc39e0.jpg","danmaku":19,"view":29419,"pubdate":1544187665,"vt":0,"status":"completed","active":true,"loaded":true,"qn":80,"allowHEVC":false,"createTime":1742792974202,"coverPath":"/Users/lidongxuan/Movies/bilibili/66158339/image.jpg","groupCoverPath":"/Users/lidongxuan/Movies/bilibili/66158339/group.jpg","updateTime":1742793070794,"totalSize":95036588,"loadedSize":95036588,"progress":100,"speed":0,"completionTime":1742793070756,"reportedSize":95036588}