{"type":"ugc","codecid":7,"groupId":"BV1W2RbYiEXB","itemId":28774370212,"aid":114130937712428,"cid":28774370212,"bvid":"BV1W2RbYiEXB","p":1,"tabP":0,"tabName":"城市风景素材【无水印】","uid":"491797842","uname":"风景素材来了","avatar":"https://i0.hdslb.com/bfs/face/7dd083caad25f019fb6abec6dbe8c5191eac6679.jpg","coverUrl":"http://i2.hdslb.com/bfs/archive/f2dc361a980172345e653b398a104e5e51c2b62a.jpg","title":"城市风景素材【无水印】","duration":76,"groupTitle":"城市风景素材【无水印】","groupCoverUrl":"http://i2.hdslb.com/bfs/archive/f2dc361a980172345e653b398a104e5e51c2b62a.jpg","danmaku":0,"view":395,"pubdate":1741500035,"vt":0,"status":"completed","active":true,"loaded":true,"qn":80,"allowHEVC":false,"createTime":1742804242142,"coverPath":"/Users/lidongxuan/Movies/bilibili/28774370212/image.jpg","groupCoverPath":"/Users/lidongxuan/Movies/bilibili/28774370212/group.jpg","updateTime":1742804267340,"totalSize":35738677,"loadedSize":35738677,"progress":100,"speed":0,"completionTime":1742804267316,"reportedSize":35738677}